{
  "音速犬::最终形态": {
    "status": "已核对-无差异",
    "summary": "洛克王国世界资料评价其速度与物攻突出，属于先手输出型精灵；与本地“物攻输出 / 高速先手”一致。旧网页洛克王国资料已排除。",
    "source": "豌豆荚：https://m.wandoujia.com/apps/8100514/12274742904409534266.html；搜索日期：2026-07-09"
  },
  "彩蝶鲨::最终形态": {
    "status": "已核对-无差异",
    "summary": "洛克王国世界资料更强调速度、控制/技能效果和魔攻输出倾向；本地在耐久阈值收紧后已移除强耐久标签，主要定位回到高速节奏/能量循环/魔法技能线，暂判与外部定位更一致。",
    "source": "3DM：https://ol.3dmgame.com/gl/337408.html；BWIKI：https://wiki.biligame.com/rocom/彩蝶鲨；搜索日期：2026-07-09"
  },
  "白金独角兽::最终形态": {
    "status": "已核对-无差异",
    "summary": "洛克王国世界资料评价其魔攻和速度突出，符合魔法高速输出定位；与本地“魔攻输出 / 高速先手”一致。",
    "source": "豌豆荚：https://m.wandoujia.com/apps/8100514/8804251513711481370.html；搜狐：https://www.sohu.com/a/890910762_121963726；搜索日期：2026-07-09"
  },
  "黑猫巫师::最终形态": {
    "status": "已核对-无差异",
    "summary": "洛克王国世界资料评价其魔攻、速度突出，适合作为速攻魔法输出；与本地魔攻输出和速度线一致。",
    "source": "3DM：https://ol.3dmgame.com/gl/337516.html；豌豆荚：https://m.wandoujia.com/apps/8100514/1054053429764449975.html；搜索日期：2026-07-09"
  },
  "影狸::最终形态": {
    "status": "已核对-无差异",
    "summary": "洛克王国世界资料评价其速度优势明显；本地仍保留双攻面板，但已允许技能组明显偏物理时把魔攻降级为单攻分支风险，因此当前推荐以高速物理路线为主、双攻可能作为风险提示保留，暂判与定位口径一致。",
    "source": "3DM：https://ol.3dmgame.com/gl/337518.html；豌豆荚：https://m.wandoujia.com/apps/8100514/6375325330263313946.html；用户确认双攻精灵可由技能组证明单攻分支；搜索日期：2026-07-09"
  },
  "圣羽翼王::最终形态": {
    "status": "待人工确认",
    "summary": "用户补充“迅捷”机制：主动切换精灵上场时会自动释放第一个能耗足够且带迅捷词条的技能，并必定先手；若双方都是迅捷技能则比较速度。当前已新增迅捷触发标签与速度风险解释，仍需后续确认翼王是否主要按频繁切换触发迅捷的启动/轮转压制来建模。旧网页洛克王国资料已排除。",
    "source": "什么值得买：https://post.smzdm.com/p/az8w3635；用户机制说明：迅捷切入自动先手释放且同迅捷拼速度；搜索日期：2026-07-09"
  },
  "圆号鱼::最终形态": {
    "status": "核对中",
    "summary": "已找到洛克王国世界图鉴/技能搭配资料，外部更强调水火技能和喧哗干扰，但缺少稳定的定位评价；需继续搜索视频/社区来源。",
    "source": "17173：https://news.17173.com/z/lkwgsj/content/04232025/110938055.shtml；BWIKI：https://wiki.biligame.com/rocom/圆号鱼；搜索日期：2026-07-09"
  },
  "迷迷箱怪::最终形态": {
    "status": "待人工确认",
    "summary": "洛克王国世界资料对其输出方向存在分歧，有的强调物攻/双向，有的强调魔法输出；本地暂无推荐，需确认技能版本与实际定位口径。",
    "source": "3DM：https://ol.3dmgame.com/gl/337695.html；17173：https://news.17173.com/z/lkwgsj/content/04232025/215208821.shtml；搜索日期：2026-07-09"
  },
  "裘卡::最终形态": {
    "status": "待人工确认",
    "summary": "洛克王国世界资料评价其速度线重要，但物攻/魔攻路线仍需结合技能确认；与本地重视速度大体一致，需继续确认攻击方向。旧网页洛克王国资料已排除。",
    "source": "3DM：https://ol.3dmgame.com/gl/337720.html；搜索日期：2026-07-09"
  },
  "冰钻布鲁斯::最终形态": {
    "status": "待人工确认",
    "summary": "洛克王国世界资料能确认其物攻倾向与较高物防，但低生命导致实战肉度仍有争议；结合用户反馈“评价很脆”，需要继续核对社区/视频对低生命的评价。",
    "source": "3DM：https://ol.3dmgame.com/gl/337722.html；豌豆荚：https://m.wandoujia.com/apps/8100514/7748344484480778216.html；BWIKI：https://wiki.biligame.com/rocom/冰钻布鲁斯；搜索日期：2026-07-09"
  },
  "寂灭骨龙::最终形态": {
    "status": "已核对-无差异",
    "summary": "洛克王国世界资料集中在技能与机制，整体支持物攻和一定耐久/后手机制；与本地主物攻方向一致，后手/耐久仍可继续细核。旧网页洛克王国资料已排除。",
    "source": "豌豆荚：https://m.wandoujia.com/apps/8100514/11262448109933625767.html；搜索日期：2026-07-09"
  }
}
